[
  {
    "chinese": "我需要去银行",
    "thai": "ฉันต้องไปธนาคาร",
    "pinyin": "missing pinyin"
  },
  {
    "chinese": "我想开户",
    "thai": "ฉันต้องการเปิดบัญชี",
    "pinyin": "missing pinyin"
  },
  {
    "chinese": "我想销户",
    "thai": "ฉันต้องการยกเลิกบัญชีของฉัน",
    "pinyin": "missing pinyin"
  },
  {
    "chinese": "我想转账",
    "thai": "ฉันต้องการโอนเงิน",
    "pinyin": "missing pinyin"
  },
  {
    "chinese": "我想取钱",
    "thai": "ฉันต้องการถอนเงิน",
    "pinyin": "missing pinyin"
  },
  {
    "chinese": "我想存钱",
    "thai": "ฉันอยากประหยัดเงิน",
    "pinyin": "missing pinyin"
  },
  {
    "chinese": "...的汇率是多少",
    "thai": "อัตราแลกเปลี่ยนเป็นเท่าไหร่สำหรับ...",
    "pinyin": "missing pinyin"
  },
  {
    "chinese": "我需要寄一个包裹",
    "thai": "ฉันต้องส่งพัสดุ",
    "pinyin": "missing pinyin"
  },
  {
    "chinese": "寄这个多少钱",
    "thai": "ส่งแบบนี้เสียค่าส่งเท่าไหร่คะ?",
    "pinyin": "missing pinyin"
  },
  {
    "chinese": "我需要买邮票",
    "thai": "ฉันต้องการซื้อแสตมป์",
    "pinyin": "missing pinyin"
  },
  {
    "chinese": "邮局在哪里",
    "thai": "ที่ทำการไปรษณีย์อยู่ที่ไหน?",
    "pinyin": "missing pinyin"
  },
  {
    "chinese": "我需要取包裹",
    "thai": "ฉันต้องไปรับพัสดุ",
    "pinyin": "missing pinyin"
  },
  {
    "chinese": "我需要签收吗",
    "thai": "ฉันจำเป็นต้องเซ็นชื่อมั้ย?",
    "pinyin": "missing pinyin"
  },
  {
    "chinese": "你们的营业时间是什么",
    "thai": "เวลาเปิดทำการของคุณคืออะไร?",
    "pinyin": "missing pinyin"
  },
  {
    "chinese": "附近有公共厕所吗",
    "thai": "มีห้องน้ำสาธารณะใกล้ๆ ไหม?",
    "pinyin": "missing pinyin"
  },
  {
    "chinese": "我需要找药店",
    "thai": "ฉันต้องหาร้านขายยา",
    "pinyin": "missing pinyin"
  },
  {
    "chinese": "我需要买药",
    "thai": "ฉันต้องซื้อยา",
    "pinyin": "missing pinyin"
  },
  {
    "chinese": "我需要处方吗",
    "thai": "ฉันต้องมีใบสั่งยาไหม?",
    "pinyin": "missing pinyin"
  },
  {
    "chinese": "我应该多久服用一次",
    "thai": "ฉันควรทานบ่อยแค่ไหน",
    "pinyin": "missing pinyin"
  },
  {
    "chinese": "有什么副作用吗",
    "thai": "มีผลข้างเคียงมั้ย?",
    "pinyin": "missing pinyin"
  }
]