[
  {
    "english": "Reading",
    "thai": "การอ่าน",
    "phonetic": ""
  },
  {
    "english": "Writing",
    "thai": "การเขียน",
    "phonetic": ""
  },
  {
    "english": "Drawing",
    "thai": "การวาดภาพ",
    "phonetic": ""
  },
  {
    "english": "Photography",
    "thai": "การถ่ายภาพ",
    "phonetic": ""
  },
  {
    "english": "Cooking",
    "thai": "การทำอาหาร",
    "phonetic": ""
  },
  {
    "english": "Baking",
    "thai": "การอบขนม",
    "phonetic": ""
  },
  {
    "english": "Hiking",
    "thai": "การเดินป่า",
    "phonetic": ""
  },
  {
    "english": "Camping",
    "thai": "การตั้งแคมป์",
    "phonetic": ""
  },
  {
    "english": "Fishing",
    "thai": "การตกปลา",
    "phonetic": ""
  },
  {
    "english": "Swimming",
    "thai": "การว่ายน้ำ",
    "phonetic": ""
  },
  {
    "english": "Running",
    "thai": "วิ่ง",
    "phonetic": ""
  },
  {
    "english": "Cycling",
    "thai": "การปั่นจักรยาน",
    "phonetic": ""
  },
  {
    "english": "Dancing",
    "thai": "เต้นรำ",
    "phonetic": ""
  },
  {
    "english": "Singing",
    "thai": "การร้องเพลง",
    "phonetic": ""
  },
  {
    "english": "Guitar",
    "thai": "กีตาร์",
    "phonetic": ""
  },
  {
    "english": "Piano",
    "thai": "เปียโน",
    "phonetic": ""
  },
  {
    "english": "Movies",
    "thai": "ภาพยนตร์",
    "phonetic": ""
  },
  {
    "english": "Music",
    "thai": "ดนตรี",
    "phonetic": ""
  },
  {
    "english": "Opera",
    "thai": "โอเปร่า",
    "phonetic": ""
  },
  {
    "english": "Ballet",
    "thai": "บัลเล่ต์",
    "phonetic": ""
  }
]